README.txt
setup.py
collective/__init__.py
collective.lorem.egg-info/PKG-INFO
collective.lorem.egg-info/SOURCES.txt
collective.lorem.egg-info/dependency_links.txt
collective.lorem.egg-info/entry_points.txt
collective.lorem.egg-info/namespace_packages.txt
collective.lorem.egg-info/not-zip-safe
collective.lorem.egg-info/requires.txt
collective.lorem.egg-info/top_level.txt
collective/lorem/__init__.py
collective/lorem/archetypes.py
collective/lorem/archetypes.zcml
collective/lorem/browser.py
collective/lorem/configure.zcml
collective/lorem/corpus.txt
collective/lorem/generation.py
collective/lorem/generation.txt
collective/lorem/interfaces.py
collective/lorem/setuphandlers.py
collective/lorem/tests.py
collective/lorem/profiles/out-of-the-box/import_steps.xml
collective/lorem/profiles/out-of-the-box/marker.txt
collective/lorem/profiles/ui/actions.xml
collective/lorem/resources/ferret.jpg
collective/lorem/resources/lipsum.pdf
