Metadata-Version: 1.0
Name: collective.lorem
Version: 0.2.3
Summary: A package that provides dummy content generation.
Home-page: UNKNOWN
Author: Malthe Borch
Author-email: mborch@gmail.com
License: BSD
Platform: UNKNOWN
Classifier: Framework :: Plone
Classifier: Framework :: Zope2
Classifier: Framework :: Zope3
Classifier: Programming Language :: Python
Classifier: Topic :: Software Development :: Libraries :: Python Modules
